Workbook

Sheet 1. Business Case
A1: Barefoot Addo Elephant Lodge — Own-Network Business Case
A2: Why build a private carrier-grade network instead of continuing to rent one, month after month, forever.
A4: Prepared for: Barefoot Addo Elephant Lodge (Pty) Ltd owners (Port Elizabeth)
A5: Prepared by: Gerhard Smit, CTTX Services (Pty) Ltd
A6: Date: 26 September 2026
A8: The Simple Version
A9: Right now the lodge pays a monthly bill to Herotel forever, for equipment it will never own, on a network it does not control. This proposal is the alternative: pay once to build a private network on your own engineered mast, then pay a much smaller monthly fee for the carrier link that feeds it. The network is built to run for 10 years, and CTTX supports it for that whole period.
A13: Headline Numbers
A14: One-time build cost (infrastructure, owned by the lodge) | E14: ='2. CAPEX Build Cost'!E40
A15: Current Herotel monthly bill (connectivity + rented Wi-Fi equipment) | E15: ='3. Monthly Cost Comparison'!C11
A16: New monthly bill once built (Vodacom link + CTTX monitoring - recommended) | E16: ='3. Monthly Cost Comparison'!C26
A17: Monthly saving once built | E17: =E15-E16
A18: Time to pay back the build cost | E18: ='4. 10-Year Cash Flow'!B28
A19: Total saved over 10 years vs staying with Herotel | E19: ='4. 10-Year Cash Flow'!M30
A21: Why This Makes Sense Over 10 Years
A22: 1. The lodge currently pays for connectivity AND for the right to use someone else's Wi-Fi equipment, every month, indefinitely. Nothing is ever owned.
A23: 2. The existing backhaul radios are mounted on a leaning gum pole - not an engineered structure. That is a physical failure risk, separate from the cost problem.
A24: 3. Building a private network converts a forever-rising monthly rental into a one-time build cost plus a much smaller ongoing carrier fee for just the connectivity - the Wi-Fi equipment, the mast, and the solar power all become the lodge's own asset.
A25: 4. CTTX designs, builds, and supports this network for an expected 10-year working life - see tab 5 for what that support includes and excludes.
A26: 5. See tab 4 for the year-by-year numbers: the build cost is recovered from the monthly saving within the payback period shown above, and every month after that is money the lodge keeps instead of sending to a telecoms reseller.
A28: Full cost detail: tab 2 (build cost), tab 3 (monthly comparison), tab 4 (10-year cash flow), tab 5 (assumptions - read this before trusting any number on this page).

Sheet 2. CAPEX Build Cost
A1: One-Time Build Cost (CAPEX)
A2: All prices exclude VAT unless marked. Source: Duxbury Networking Quote DUX00455421 v2 + CTTX rate card + CTTX labour estimate.
A4: Hardware BOM
A5: Item | B5: Model | C5: Qty | D5: Unit Price | E5: Total
A6: Backhaul Base Station | B6: Cambium ePMP 4500L 5GHz AP, 2x2, AC PoE | C6: 2 | D6: 8470 | E6: =C6*D6
A7: Sector Antenna | B7: ePMP Sector Antenna 5GHz 90/120deg | C7: 2 | D7: 3209 | E7: =C7*D7
A8: Subscriber Modules | B8: Cambium ePMP Force 4525L, 25dBi | C8: 28 | D8: 2745 | E8: =C8*D8
A9: Indoor Access Points | B9: DuxNet Wi-Fi 6 Ceiling AP, 1Gb WAN/LAN | C9: 28 | D9: 1025 | E9: =C9*D9
A10: Outdoor Access Points | B10: DuxNet Outdoor Dual-Band Wi-Fi 6 AP | C10: 2 | D10: 1885 | E10: =C10*D10
A11: Network Switches | B11: DuxNet 8-Port Gigabit PoE+ L2 Cloud Switch | C11: 4 | D11: 1899 | E11: =C11*D11
A12: Hardware Subtotal | E12: =SUM(E6:E11)
A14: Outdoor Infrastructure & Civil
A15: Not standard rate-card items - priced as supplier/stock quotes specific to this site (per Gerhard, confirmed 25-26 Sept 2026).
A16: Item | B16: Model | C16: Qty | D16: Unit Price | E16: Total
A17: 9m Steel Mast with Plinth, installed | B17: CTTX second-hand stock; replaces existing gum-pole mount | C17: 1 | D17: 38700 | E17: =C17*D17
A18: Outdoor Cabinet | B18: w/ MPPT Charge Controller & Lithium Battery Switchgear | C18: 1 | D18: 28670 | E18: =C18*D18
A19: Solar Panels | B19: Canadian Solar 680W Monocrystalline | C19: 4 | D19: 2200 | E19: =C19*D19
A20: Grid/Solar Inverter | C20: 1 | D20: 2150 | E20: =C20*D20
A21: Outdoor Cabling | B21: Mast-to-cabinet, WAN, AP runs (avg. 40m run - confirm at survey) | C21: 40 | D21: 12 | E21: =C21*D21
A22: Mounting Brackets & Hardware | B22: Radio, AP, and solar mounts | C22: 15 | D22: 450 | E22: =C22*D22
A23: Infrastructure Subtotal | E23: =SUM(E17:E22)
A25: Labour
A26: Task | B26: Notes | C26: Days/Units | D26: Rate | E26: Total
A27: Site survey and design | B27: 1 day | C27: 1 | D27: 4500 | E27: =C27*D27
A28: Installation (AP deployment, cabling, PoE, switch config) | B28: 2-tech team, 3 days | C28: 3 | D28: 9000 | E28: =C28*D28
A29: Commissioning and testing | B29: 1 day | C29: 1 | D29: 4500 | E29: =C29*D29
A30: Documentation and handover | B30: 1 half-day | C30: 1 | D30: 2250 | E30: =C30*D30
A31: Labour Subtotal | E31: =SUM(E27:E30)
A32: Travel/accommodation not applied - day-trip distance from PE assumed; confirm at survey.
A33: Trenching: not applicable - wireless solution, no underground civil works required.
A35: Project Total
A36: Subtotal (Hardware + Infrastructure + Labour) | E36: =E12+E23+E31
A37: Contingency | D37: 0.1 | E37: =E36*D37
A38: Project Total (Excl. VAT) | E38: =E36+E37
A39: VAT | D39: 0.15 | E39: =E38*D39
A40: TOTAL BUILD COST (Incl. VAT) | E40: =E38+E39

Sheet 3. Monthly Cost Comparison
A1: Monthly Cost — Current (Herotel) vs Proposed (CTTX)
A2: Herotel figures from Tax Invoice #8313058, dated 31 Aug 2026. CTTX/Vodacom figures are the confidential-cost-protected client price from the CTTX Vodacom Reseller Pricing Master (Notion, updated 15 June 2026) - never the underlying CTTX cost.
A4: Current: Herotel Business (what the lodge pays today)
A5: Item | B5: Excl. VAT | C5: Incl. VAT
A6: Business WTTB 100 Mbps Symmetrical | B6: 9999 | C6: 11498.85
A7: Static IP | B7: 180 | C7: 207
A8: Huawei Wi-Fi 6 AP 362 (Managed-lite, 9x 24-month term) | B8: 2061 | C8: 2370.15
A9: HB Managed Wi-Fi (Lite) 0-5 (x2) | B9: 298 | C9: 342.7
A10: Huawei Wi-Fi 6 AP 362 (Managed-lite, 14x 12-month term) | B10: 3206 | C10: 3686.9
A11: Herotel Monthly Total (current) | B11: =SUM(B6:B10) | C11: =SUM(C6:C10)
A13: Proposed: Vodacom Business Connect via CTTX (carrier connectivity only)
A14: Uncontended (1:1), Uncapped, Unshaped, No FUP, Symmetrical, Business SLA, Huawei router included, 1 static IP standard. 24-month contract. Subject to feasibility confirmation.
A15: Item | B15: Excl. VAT | C15: Incl. VAT
A16: Vodacom Business Connect 100 Mbps (Monthly Recurring Charge) | B16: 7103 | C16: 8168
A17: Once-off Connection Fee (NRC) - not monthly, shown for reference | B17: 3130 | C17: 3599
A18: Vodacom-Only Monthly Total | B18: =B16 | C18: =C16
A20: Optional Add-On: CTTX Managed Service Retainer (recommended)
A21: Remote monitoring (Cambium cnMaestro + Victron), proactive maintenance, quarterly on-site visits, battery/solar health checks, priority emergency support. CTTX does not deploy unmonitored infrastructure as a matter of policy.
A22: Item | B22: Excl. VAT | C22: Incl. VAT
A23: Managed Service Retainer (mid-tier of R3,500-R5,500 range) | B23: 4500 | C23: 5175
A25: Recommended Path: Vodacom + Managed Retainer
A26: Recommended Monthly Total (Vodacom + Retainer) | B26: =B16+B23 | C26: =C16+C23
A27: Monthly saving vs Herotel (recommended path, incl. VAT) | C27: =C11-C26
A28: Monthly saving vs Herotel (Vodacom-only, self-maintained, incl. VAT) | C28: =C11-C18

Sheet 4. 10-Year Cash Flow
A1: 10-Year Cash Flow — Build vs Keep Renting
A2: Year 0 = build year (deposit and construction). Years 1-10 = the network's expected working life under CTTX support. All figures incl. VAT.
A4: Annual escalation rate (applied to both Herotel and Vodacom monthly fees) | B4: 0.08 | C4: <- editable assumption; see tab 5 for why 8% was used
A6: Year | B6: 0 | C6: 1 | D6: 2 | E6: 3 | F6: 4 | G6: 5 | H6: 6 | I6: 7 | J6: 8 | K6: 9 | L6: 10
A7: Path A: Stay with Herotel (do nothing)
A8: Herotel monthly bill (escalated) | B8: ='3. Monthly Cost Comparison'!$C$11 | C8: =B8*(1+$B$4) | D8: =C8*(1+$B$4) | E8: =D8*(1+$B$4) | F8: =E8*(1+$B$4) | G8: =F8*(1+$B$4) | H8: =G8*(1+$B$4) | I8: =H8*(1+$B$4) | J8: =I8*(1+$B$4) | ... L8: =K8*(1+$B$4)
A9: Herotel annual cost | B9: =B8*12 | C9: =C8*12 | D9: =D8*12 | E9: =E8*12 | F9: =F8*12 | G9: =G8*12 | H9: =H8*12 | I9: =I8*12 | ... L9: =L8*12
A10: Herotel cumulative cost | B10: =B9 | C10: =B10+C9 | D10: =C10+D9 | E10: =D10+E9 | F10: =E10+F9 | G10: =F10+G9 | H10: =G10+H9 | I10: =H10+I9 | J10: =I10+J9 | ... L10: =K10+L9
A12: Path B: Build the CTTX private network (recommended - Vodacom + Managed Retainer)
A13: Build cost (one-time, Year 0 only) | B13: ='2. CAPEX Build Cost'!$E$40 | C13: 0 | D13: 0 | E13: 0 | F13: 0 | G13: 0 | H13: 0 | I13: 0 | J13: 0 | K13: 0 | L13: 0
A14: Vodacom once-off connection fee (Year 0 only) | B14: ='3. Monthly Cost Comparison'!$C$17 | C14: 0 | D14: 0 | E14: 0 | F14: 0 | G14: 0 | H14: 0 | I14: 0 | J14: 0 | K14: 0 | L14: 0
A15: CTTX monthly recurring (Vodacom + Retainer, escalated) | B15: 0 | C15: ='3. Monthly Cost Comparison'!$C$26 | D15: =C15*(1+$B$4) | E15: =D15*(1+$B$4) | F15: =E15*(1+$B$4) | G15: =F15*(1+$B$4) | H15: =G15*(1+$B$4) | I15: =H15*(1+$B$4) | J15: =I15*(1+$B$4) | K15: =J15*(1+$B$4) | L15: =K15*(1+$B$4)
A16: CTTX annual recurring cost | B16: =B15*12 | C16: =C15*12 | D16: =D15*12 | E16: =E15*12 | F16: =F15*12 | G16: =G15*12 | H16: =H15*12 | I16: =I15*12 | ... L16: =L15*12
A17: CTTX cumulative cost | B17: =B13+B14+B16 | C17: =B17+C16 | D17: =C17+D16 | E17: =D17+E16 | F17: =E17+F16 | G17: =F17+G16 | H17: =G17+H16 | I17: =H17+I16 | J17: =I17+J16 | ... L17: =K17+L16
A19: Cumulative Savings (Path A minus Path B)
A20: Cumulative savings from building (negative = still paying off the build) | B20: =B10-B17 | C20: =C10-C17 | D20: =D10-D17 | E20: =E10-E17 | F20: =F10-F17 | G20: =G10-G17 | H20: =H10-H17 | I20: =I10-I17 | ... L20: =L10-L17
A22: Payback Calculation
A23: Last year cumulative savings still negative or zero (position in range) | B23: =MATCH(0,B20:L20,1)
A24: That year number | B24: =INDEX(B6:L6,B23)
A25: Cumulative savings at that year | B25: =INDEX(B20:L20,B23)
A26: Cumulative savings the following year | B26: =INDEX(B20:L20,B23+1)
A27: Payback point (years, decimal) | B27: =B24+(-B25)/(B26-B25)
A28: Payback point (plain English) | B28: =TEXT(INT(B27),"0")&" years, "&TEXT(ROUND((B27-INT(B27))*12,0),"0")&" months"
A30: Total 10-year saving vs Herotel (recommended path) | M30: =L20

Sheet 5. Assumptions & Scope
A1: Assumptions, Scope, and What's Not Yet Confirmed
A3: Financial Assumptions
A4: Assumption | B4: Value | C4: Basis
A5: Annual price escalation (Herotel and Vodacom) | B5: 8% p.a. | C5: Not confirmed by either party - a typical CPI-linked telecom escalation in South Africa. Editable on tab 4; change it and every formula recalculates.
A6: Contingency on build cost | B6: 10% | C6: Standard CTTX estimating practice for a project at this stage (pre-final-survey).
A7: VAT rate | B7: 15% | C7: Current South African VAT rate.
A8: Managed Service Retainer | B8: R4,500/month excl. VAT | C8: Mid-point of CTTX's R3,500-R5,500/month range for a system this complex (mast, solar/battery, 30 radios).
A9: Contract term - Vodacom Business Connect | B9: 24 months | C9: Standard Vodacom Business Connect contract term. The network's physical life (10 years) is longer than this contract term - Vodacom connectivity is expected to be renewed at then-current rates.
A11: Design Assumptions
A12: Single 9m mast carrying two 90-degree sector antennas (confirmed by Gerhard, 26 Sept 2026) - replaces the lodge's existing leaning gum-pole mount. This is NOT a two-site build; earlier drafts of this costing incorrectly read the field survey's two radio labels as two separate physical locations before this was corrected.
A13: Line-of-sight confirmed for all 28 subscriber links by Abel Ringisai's field RF survey (KML export, 22 Sept 2026).
A14: The longest links (1.7km-3.0km, to the staff village and Director's House) sit at the edge of the serving sector's range and still need a link-budget check to confirm they sustain full 100 Mbps symmetrical - flagged, not yet resolved.
A15: Cable run priced at an average 40m per run - to be confirmed once exact distances are measured on site.
A16: Vodacom Business Connect feasibility for this specific site has not yet been formally submitted/approved.
A18: What's Included in the 10-Year Support
A19: Years 1-3: monthly remote monitoring, quarterly on-site maintenance, 24/7 emergency support, proactive performance reporting, warranty-covered equipment troubleshooting/replacement.
A20: Years 4-10: ongoing remote monitoring, annual on-site maintenance/assessment, 24/7 support continuation, planned technology refresh, performance reporting.
A21: Throughout: no vendor lock-in on the owned hardware, scalability support, staff training and documentation.
A23: What's Excluded / Not Yet Priced
A24: Major component replacement (Lithium battery bank, inverter) near the end of the 10-year term - typical service life for this equipment is 8-10 years, so a replacement reserve may be needed in years 8-10 and is not included in the build cost above.
... A28: Any scope beyond the confirmed coverage zones (28 subscriber sites) without a signed change order.
