Workbook

Sheet Detailed Cost Schedule
A1: Barefoot Addo Elephant Lodge — Hybrid Network: Detailed Cost Schedule
A2: CTTX Services (Pty) Ltd · Prepared for Barefoot Addo Elephant Lodge (Pty) Ltd · 29 September 2026 · All prices in ZAR, excluding VAT unless stated · Valid 30 days
A4: # | B4: Item | C4: Qty | D4: Unit price | E4: Line total | F4: Note
B5: A. Backbone — mast, base station and power
A6: 1 | B6: 6 m galvanised steel mast with concrete plinth, holding-down bolts and earthing, installed | C6: 1 | D6: 25943.84 | E6: =C6*D6 | F6: Replaces the existing gum pole
A7: 2 | B7: Cambium ePMP 4500L base station radio (5 GHz) | C7: 2 | D7: 9988.38 | E7: =C7*D7 | F7: Two sectors covering the whole property
A8: 3 | B8: Sector antenna, 120°, with mounting kit | C8: 2 | D8: 3784.26 | E8: =C8*D8
A9: 4 | B9: Weatherproof outdoor equipment cabinet | C9: 1 | D9: 9434.13 | E9: =C9*D9
A10: 5 | B10: Solar power system: 2 × 660 W panels, Victron MPPT charge controller, 5.3 kWh lithium (LFP) battery, 5 kW off-grid inverter, DC/AC distribution and protection | C10: 1 | D10: 30602.91 | E10: =C10*D10 | F10: Mast runs independently of Eskom
B11: Subtotal — A. Backbone — mast, base station and power | E11: =SUM(E6:E10)
B13: B. Distribution — wireless links to buildings
A14: 6 | B14: Cambium ePMP Force 4525L subscriber radio, 25 dBi — main lodge, villas, spa, school, workshop and boma cluster | C14: 15 | D14: 3237.08 | E14: =C14*D14 | F14: One per building
A15: 7 | B15: Cambium ePMP Force 4525L subscriber radio, 25 dBi — staff village and Director's House | C15: 10 | D15: 3237.08 | E15: =C15*D15 | F15: 2.3–3 km links
A16: 8 | B16: Radio mounting brackets and hardware | C16: 25 | D16: 530.67 | E16: =C16*D16
A17: 9 | B17: Outdoor Ethernet cable, connectors and weatherproofing (average 40 m per building) | C17: 1000 | D17: 14.15 | E17: =C17*D17 | F17: Per metre
B18: Subtotal — B. Distribution — wireless links to buildings | E18: =SUM(E14:E17)
B20: C. Wi-Fi and switching
A21: 10 | B21: Wi-Fi 6 indoor ceiling access point | C21: 22 | D21: 1208.75 | E21: =C21*D21 | F21: Guest rooms, staff houses, offices
A22: 11 | B22: Wi-Fi 6 outdoor access point | C22: 4 | D22: 2222.92 | E22: =C22*D22 | F22: Main lodge, villa, boma and spa exteriors
A23: 12 | B23: 8-port gigabit PoE+ managed switch (cloud-managed) | C23: 2 | D23: 2239.43 | E23: =C23*D23
A24: 13 | B24: 6-port PoE switch | C24: 2 | D24: 766.52 | E24: =C24*D24
A25: 14 | B25: 4U wall-mount equipment enclosure | C25: 4 | D25: 707.56 | E25: =C25*D25
B26: Subtotal — C. Wi-Fi and switching | E26: =SUM(E21:E25)
B28: D. Installation, commissioning and handover
A29: 15 | B29: Site survey, RF design and link planning | C29: 1 | D29: 5306.7 | E29: =C29*D29 | F29: Completed 22 Sep 2026
A30: 16 | B30: Installation — two-technician team, mast, radios, access points, cabling and power | C30: 3 | D30: 10613.39 | E30: =C30*D30 | F30: Per day
A31: 17 | B31: Commissioning, link testing and Wi-Fi coverage verification | C31: 1 | D31: 5306.7 | E31: =C31*D31
A32: 18 | B32: Documentation, training and handover | C32: 1 | D32: 2654.55 | E32: =C32*D32
B33: Subtotal — D. Installation, commissioning and handover | E33: =SUM(E29:E32)
B35: TOTAL — network build, excluding VAT | E35: =E11+E18+E26+E33
B36: VAT at 15% | E36: =E35*0.15
B37: TOTAL — network build, including VAT | E37: =E35+E36
B39: Payment terms: 50% on order (secures the equipment allocation and places the order), 50% on commissioning.
B40: Ownership: all equipment, the mast, the cabinet and the power system are the property of Barefoot Addo Elephant Lodge (Pty) Ltd on handover.
B41: Included: design, delivery to site, installation, configuration, testing, documentation and training. Manufacturer warranties apply (Cambium 12 months; extended 2-year cover available as an option on request).
B42: Not included: the Vodacom carrier link (see Monthly Costs), trenching or civil works beyond the mast plinth, Eskom connections, and any building works.

Sheet Monthly Costs
A1: Monthly costs — today versus after the build
A2: Including VAT. Current figures from the lodge's August 2026 invoice. Proposed figures fixed for the 36-month agreement.
A4: Item | B4: Excl. VAT | C4: Incl. VAT | D4: Note
A5: Today — current provider
A6: Business wireless 100 Mbps symmetrical (shared) + static IP | B6: 10179 | C6: =B6*1.15 | D6: Rented connection
A7: Rented Wi-Fi access points — 23 units on 12- and 24-month terms | B7: 5267 | C7: =B7*1.15 | D7: Rented, never owned
A8: Managed Wi-Fi service (2 sites) | B8: 298 | C8: =B8*1.15
A9: Current monthly total | B9: =SUM(B6:B8) | C9: =SUM(C6:C8)
A11: After the build — CTTX hybrid network
A12: Vodacom Business Connect 100 Mbps — uncontended 1:1, symmetrical, uncapped, unshaped, Business SLA, LTE backup, static IP (36-month term) | B12: 4982.45 | C12: =B12*1.15 | D12: Carrier link, fixed for 36 months
A13: CTTX managed service: remote monitoring, maintenance, quarterly site visits, priority support | B13: 1500 | C13: =B13*1.15 | D13: Fixed for 36 months
A14: Wi-Fi equipment rental | B14: 0 | C14: =B14*1.15 | D14: None — the lodge owns the network
A15: Proposed monthly total | B15: =SUM(B12:B14) | C15: =SUM(C12:C14)
A17: Monthly saving | B17: =B9-B15 | C17: =C9-C15
A18: Reduction in the monthly bill | C18: =C17/C9
A19: Saving per year | C19: =C17*12
A20: Saving over the 36-month agreement | C20: =C17*36
A22: Once-off: Vodacom connection fee | B22: 3129.4 | C22: =B22*1.15 | D22: Payable once the link is installed

Sheet Payment Options
A1: Two ways to pay for the same network
A2: Including VAT. Option 2 is an illustration of an asset-finance facility the lodge would arrange directly with its bank or a finance house; CTTX is not the lender.
A4: Option 1 — Buy outright
A5: Network build (incl. VAT) | B5: ='Detailed Cost Schedule'!E37
A6: 50% on order | B6: =B5*0.5
A7: 50% on commissioning | B7: =B5*0.5
A8: Monthly thereafter (carrier + managed service) | B8: ='Monthly Costs'!C15
A9: Monthly saving vs today | B9: ='Monthly Costs'!C17
A10: Build cost recovered from savings in (months) | B10: =B5/B9
A12: Option 2 — Finance the build over 36 months (illustration)
A13: Indicative interest rate p.a. | B13: 0.12 | C13: Editable — subject to the lender's terms
A14: Term (months) | B14: 36
A15: Monthly instalment on the build | B15: =PMT(B13/12,B14,-B5)
A16: Plus carrier + managed service | B16: ='Monthly Costs'!C15
A17: Total per month during the 36 months | B17: =B15+B16
A18: Today's monthly bill, for comparison | B18: ='Monthly Costs'!C9
A19: Difference per month (negative = less than today) | B19: =B17-B18
A20: From month 37: network owned outright, monthly drops to | B20: ='Monthly Costs'!C15
A22: Either way the lodge owns the mast, radios, Wi-Fi and power system; the only recurring items are the carrier link and CTTX support. The order is placed only once Vodacom has confirmed feasibility of the link to the mast position.
